smart_energy_data/__init__.py
smart_energy_data/datasets/__init__.py
smart_energy_data/datasets/base_dataset.py
smart_energy_data/datasets/datasets.py
smart_energy_data/datasets/data/address.csv
smart_energy_data/datasets/data/energy_consumption.csv
smart_energy_data/datasets/data/energy_generated.csv
smart_energy_data/datasets/data/environment.csv
smart_energy_data/datasets/data/sensors.csv
smart_energy_data/datasets/data/users.json
smart_energy_data/project/__init__.py
smart_energy_data/project/secret.py
smart_energy_data/repository/__init__.py
smart_energy_data/repository/address/__init__.py
smart_energy_data/repository/address/address_dao.py
smart_energy_data/repository/address/address_dto.py
smart_energy_data/repository/address/address_mapper.py
smart_energy_data/repository/consumption/__init__.py
smart_energy_data/repository/consumption/consumption_api.py
smart_energy_data/repository/consumption/consumption_dao.py
smart_energy_data/repository/consumption/consumption_dto.py
smart_energy_data/repository/consumption/consumption_mapper.py
smart_energy_data/repository/consumption/consumption_pipeline.py
smart_energy_data/repository/env_conditions/__init__.py
smart_energy_data/repository/env_conditions/env_conditions_api.py
smart_energy_data/repository/env_conditions/env_conditions_dao.py
smart_energy_data/repository/env_conditions/env_conditions_dto.py
smart_energy_data/repository/env_conditions/env_conditions_mapper.py
smart_energy_data/repository/generation/__init__.py
smart_energy_data/repository/generation/generation_api.py
smart_energy_data/repository/generation/generation_dao.py
smart_energy_data/repository/generation/generation_dto.py
smart_energy_data/repository/generation/generation_mapper.py
smart_energy_data/repository/generation/generation_pipeline.py
smart_energy_data/repository/sensor/__init__.py
smart_energy_data/repository/sensor/sensor_dao.py
smart_energy_data/repository/sensor/sensor_dto.py
smart_energy_data/repository/sensor/sensor_mapper.py
smart_energy_data_vald3nir-1.1.2.dist-info/METADATA
smart_energy_data_vald3nir-1.1.2.dist-info/WHEEL
smart_energy_data_vald3nir-1.1.2.dist-info/licenses/LICENSE
smart_energy_data_vald3nir-1.1.2.dist-info/RECORD
